Metadata-Version: 1.0
Name: aadb
Version: 1.0.1
Summary: async with android debug bridge
Home-page: https://github.com/g1im2/aadb
Author: fxfpro
Author-email: fxfpro@163.com
License: MIT
Platform: UNKNOWN
